mape/__init__.py
mape/mape.py
mape-0.1.2.dist-info/LICENSE
mape-0.1.2.dist-info/METADATA
mape-0.1.2.dist-info/WHEEL
mape-0.1.2.dist-info/entry_points.txt
mape-0.1.2.dist-info/top_level.txt
mape-0.1.2.dist-info/RECORD
