Metadata-Version: 2.1
Name: mape
Version: 0.1.2
Summary: Method for structural preservation via Attractiveness-based Pairwise Embedding
Home-page: https://www.hannan-u.ac.jp/doctor/i_info-science/matsuda/n5fenj000002lis4.html
Author: Takeshi Matsuda
Author-email: matsuken.tit@gmail.com
License: MIT
Classifier: Programming Language :: Python :: 3
Classifier: License :: OSI Approved :: MIT License
Classifier: Operating System :: OS Independent
Classifier: Intended Audience :: Education
Classifier: Intended Audience :: Science/Research
Classifier: Topic :: Scientific/Engineering :: Artificial Intelligence
Classifier: Topic :: Scientific/Engineering :: Information Analysis
Classifier: Topic :: Scientific/Engineering :: Visualization
Classifier: Topic :: Scientific/Engineering :: Mathematics
Requires-Python: >=3.8
License-File: LICENSE
Requires-Dist: numpy<2.0,>=1.26
Requires-Dist: pandas<2.3,>=2.2
Requires-Dist: scipy<1.12,>=1.11
Requires-Dist: scikit-learn<1.5,>=1.4
Requires-Dist: matplotlib<3.9,>=3.8
Requires-Dist: torch<2.5,>=2.4
